llm_conversation_parser/__init__.py
llm_conversation_parser/cli.py
llm_conversation_parser/parser.py
llm_conversation_parser-1.0.1.dist-info/licenses/LICENSE
llm_conversation_parser-1.0.1.dist-info/METADATA
llm_conversation_parser-1.0.1.dist-info/WHEEL
llm_conversation_parser-1.0.1.dist-info/entry_points.txt
llm_conversation_parser-1.0.1.dist-info/top_level.txt
llm_conversation_parser-1.0.1.dist-info/RECORD
