Metadata-Version: 2.4
Name: llm-conversation-parser
Version: 1.0.1
Summary: A Python library for parsing LLM conversation JSON files into RAG-optimized format
Home-page: https://github.com/nullhyeon/llm-conversation-parser
Author: nullhyeon
Author-email: nullhyeon <wnsgus7832@gmail.com>
Maintainer-email: nullhyeon <wnsgus7832@gmail.com>
License: MIT
Project-URL: Homepage, https://github.com/nullhyeon/llm-conversation-parser
Project-URL: Documentation, https://github.com/nullhyeon/llm-conversation-parser#readme
Project-URL: Repository, https://github.com/nullhyeon/llm-conversation-parser
Project-URL: Issues, https://github.com/nullhyeon/llm-conversation-parser/issues
Keywords: llm,conversation,parser,rag,claude,gpt,grok,json
Classifier: Development Status :: 4 - Beta
Classifier: Intended Audience :: Developers
Classifier: License :: OSI Approved :: MIT License
Classifier: Operating System :: OS Independent
Classifier: Programming Language :: Python :: 3
Classifier: Programming Language :: Python :: 3.7
Classifier: Programming Language :: Python :: 3.8
Classifier: Programming Language :: Python :: 3.9
Classifier: Programming Language :: Python :: 3.10
Classifier: Programming Language :: Python :: 3.11
Classifier: Programming Language :: Python :: 3.12
Classifier: Topic :: Software Development :: Libraries :: Python Modules
Classifier: Topic :: Text Processing :: Markup
Classifier: Topic :: Scientific/Engineering :: Artificial Intelligence
Requires-Python: >=3.8
License-File: LICENSE
Provides-Extra: dev
Requires-Dist: pytest>=6.0; extra == "dev"
Requires-Dist: pytest-cov>=2.0; extra == "dev"
Requires-Dist: black>=21.0; extra == "dev"
Requires-Dist: flake8>=3.8; extra == "dev"
Requires-Dist: mypy>=0.800; extra == "dev"
Dynamic: author
Dynamic: home-page
Dynamic: license-file
Dynamic: requires-python
